alderaan/__init__.py
alderaan/constants.py
alderaan/ephemeris.py
alderaan/litecurve.py
alderaan/planet.py
alderaan/results.py
alderaan/legacy/alderaan/Ephemeris.py
alderaan/legacy/alderaan/LiteCurve.py
alderaan/legacy/alderaan/Planet.py
alderaan/legacy/alderaan/Results.py
alderaan/legacy/alderaan/__init__.py
alderaan/legacy/alderaan/astro.py
alderaan/legacy/alderaan/constants.py
alderaan/legacy/alderaan/detrend.py
alderaan/legacy/alderaan/dynesty_helpers.py
alderaan/legacy/alderaan/io.py
alderaan/legacy/alderaan/noise.py
alderaan/legacy/alderaan/omc.py
alderaan/legacy/alderaan/plotting.py
alderaan/legacy/alderaan/umbrella.py
alderaan/legacy/alderaan/utils.py
alderaan/legacy/alderaan/validate.py
alderaan/legacy/alderaan/version.py
alderaan/legacy/bin/analyze_autocorrelated_noise.py
alderaan/legacy/bin/combine_umbrella_samples.py
alderaan/legacy/bin/detrend_and_estimate_ttvs.py
alderaan/legacy/bin/fit_transit_shape_independent_umbrella_hmc.py
alderaan/legacy/bin/fit_transit_shape_simultaneous_nested.py
alderaan/legacy/bin/get_kepler_data.py
alderaan/modules/__init__.py
alderaan/modules/base.py
alderaan/modules/data_fetcher.py
alderaan/modules/detrend.py
alderaan/modules/omc.py
alderaan/modules/quality_control.py
alderaan/modules/quicklook.py
alderaan/modules/transit.py
alderaan/recipes/__init__.py
alderaan/recipes/alderaan_pipeline.py
alderaan/recipes/subrecipes/__init__.py
alderaan/utils/__init__.py
alderaan/utils/astro.py
alderaan/utils/io.py
alderaan/utils/pipeline.py
alderaan/utils/stats.py
alderaan-0.2.3.dist-info/licenses/LICENSE
docs/conf.py
tests/test_config.py
tests/test_ephemeris.py
tests/test_litecurve.py
tests/test_planet.py
alderaan-0.2.3.dist-info/METADATA
alderaan-0.2.3.dist-info/WHEEL
alderaan-0.2.3.dist-info/top_level.txt
alderaan-0.2.3.dist-info/RECORD
