Metadata-Version: 2.4
Name: alderaan
Version: 0.2.3
Summary: A python package for fast and robust exoplanet transit lightcurve modeling
License: MIT
Requires-Python: >=3.9
License-File: LICENSE
Requires-Dist: aesara-theano-fallback==0.1.0
Requires-Dist: arviz==0.12.1
Requires-Dist: astropy==5.3.2
Requires-Dist: celerite2==0.2.1
Requires-Dist: corner==2.2.2
Requires-Dist: cython==3.0.10
Requires-Dist: dynesty==2.1.3
Requires-Dist: exoplanet==0.5.3
Requires-Dist: exoplanet-core==0.1.2
Requires-Dist: h5py==3.9.0
Requires-Dist: ldtk==1.7.0
Requires-Dist: lightkurve==2.1.1
Requires-Dist: matplotlib==3.7.2
Requires-Dist: numba==0.55.1
Requires-Dist: numpy==1.21.6
Requires-Dist: pandas==1.5.3
Requires-Dist: pymc3==3.11.5
Requires-Dist: pymc3-ext==0.1.1
Requires-Dist: rebound==4.4.2
Requires-Dist: scipy==1.7.3
Requires-Dist: xarray==2022.9.0
Provides-Extra: dev
Requires-Dist: black==25.1.0; extra == "dev"
Requires-Dist: pylint==3.3.4; extra == "dev"
Requires-Dist: line_profiler; extra == "dev"
Requires-Dist: ipywidgets==8.1.3; extra == "dev"
Requires-Dist: notebook==6.4.13; extra == "dev"
Requires-Dist: sphinx; extra == "dev"
Requires-Dist: sphinxcontrib-napoleon; extra == "dev"
Requires-Dist: sphinx-rtd-theme; extra == "dev"
Dynamic: license-file
